{
  "$schema": "https://schema.tauri.app/config/2",
  "productName": "SeSe LuLu Translator",
  "version": "1.0.1",
  "identifier": "xyz.lncvrt.seselulu",
  "build": {
    "beforeDevCommand": "yarn dev",
    "devUrl": "http://localhost:1420",
    "beforeBuildCommand": "yarn build",
    "frontendDist": "../dist"
  },
  "app": {
    "windows": [
      {
        "title": "SeSe LuLu Translator",
        "width": 800,
        "height": 600,
        "minWidth": 600,
        "minHeight": 400,
        "maxWidth": 1280,
        "maxHeight": 720,
        "maximizable": false
      }
    ],
    "security": {
      "csp": null
    }
  },
  "bundle": {
    "active": false
  }
}
